{
  "abspath": "node-utils.js",
  "append": "node-utils.js",
  "appendFileName": "codeOrganizer.js",
  "appendSelf": "node-utils.js",
  "appendVariable": "node-utils.js",
  "appendVariable2": "node-utils.js",
  "argv": "node-utils.js",
  "assertion": "node-utils.js",
  "AssertionError": "node-utils.js",
  "backup": "node-utils.js",
  "bouncer": "node-utils.js",
  "checkpointf": "utils.js",
  "clip": "node-utils.js",
  "clip2": "node-utils.js",
  "copyFile": "node-utils.js",
  "currentFile": "node-utils.js",
  "dirFromPath": "node-utils.js",
  "dirGetter": "node-utils.js",
  "exit": "node-utils.js",
  "expandPath": "node-utils.js",
  "fileFromKey": "node-utils.js",
  "fileOrText": "node-utils.js",
  "fixChromeFilePath": "node-utils.js",
  "getDir": "node-utils.js",
  "getFile": "node-utils.js",
  "getFiles": "node-utils.js",
  "getRecentFile": "node-utils.js",
  "getString": "node-utils.js",
  "head": "node-utils.js",
  "isDir": "node-utils.js",
  "isFile": "node-utils.js",
  "isNode": "utils.js",
  "isRecentFile": "node-utils.js",
  "log": "utils.js",
  "logAction": "node-utils.js",
  "logger": "node-utils.js",
  "mergeFiles": "node-utils.js",
  "mergeJson": "node-utils.js",
  "moduleFunctionFactory": "node-utils.js",
  "mute": "node-utils.js",
  "NodeAssertion": "node-utils.js",
  "NodeError": "node-utils.js",
  "normAppend": "node-utils.js",
  "normFileDir": "node-utils.js",
  "normPrepend": "node-utils.js",
  "normRead": "node-utils.js",
  "normRpw": "node-utils.js",
  "normWrite": "node-utils.js",
  "npath": "node-utils.js",
  "openFile": "node-utils.js",
  "packageManager": "node-utils.js",
  "parseFile": "node-utils.js",
  "path": "node-utils.js",
  "prepend": "node-utils.js",
  "prettyStringify": "node-utils.js",
  "read": "node-utils.js",
  "request": "browser-utils.js",
  "rpw": "node-utils.js",
  "runUnitTest": "node-utils.js",
  "save": "node-utils.js",
  "saveSpec": "node-utils.js",
  "shunt": "node-utils.js",
  "sysArg": "node-utils.js",
  "sysArgs": "node-utils.js",
  "sysget": "node-utils.js",
  "textAndLang": "node-utils.js",
  "textGetter": "node-utils.js",
  "toRegExp": "node-utils.js",
  "unmute": "node-utils.js",
  "write": "node-utils.js",
  "writeFromOptions": "node-utils.js",
  "writeUnitTest": "node-utils.js",
  "abc": "codeOrganizer.js",
  "abf": "utils.js",
  "abrev": "utils.js",
  "AbstractMethodError": "utils.js",
  "addArrayProperty": "utils.js",
  "addDictProperty": "utils.js",
  "addExtension": "utils.js",
  "addObjectOrObjectProperty": "utils.js",
  "addProperty": "utils.js",
  "addQuotes": "utils.js",
  "allUnique": "utils.js",
  "announce": "utils.js",
  "antif": "utils.js",
  "argArgsKwargs": "utils.js",
  "argKwargSplit": "utils.js",
  "argMatch": "utils.js",
  "argo": "utils.js",
  "argParse": "utils.js",
  "argsKwargs": "utils.js",
  "argWrapFactory": "utils.js",
  "ArrayState": "utils.js",
  "arrayToDict": "utils.js",
  "assert": "utils.js",
  "assert2": "utils.js",
  "assign": "utils.js",
  "assign2": "utils.js",
  "assignFresh": "utils.js",
  "assignMethods": "utils.js",
  "assignObject": "utils.js",
  "atFirst": "utils.js",
  "atSecond": "utils.js",
  "backspace": "utils.js",
  "bind": "utils.js",
  "bindingRE": "utils.js",
  "bindObject": "utils.js",
  "blockQuote": "utils.js",
  "blue": "utils.js",
  "boundary": "utils.js",
  "boundarySplit": "utils.js",
  "brackify": "utils.js",
  "brackify2": "utils.js",
  "breaker": "utils.js",
  "bringToLife": "utils.js",
  "buildDict": "utils.js",
  "Cache": "utils.js",
  "callableArgsKwargs": "utils.js",
  "callableRE": "utils.js",
  "camelCase": "utils.js",
  "camelToDash": "utils.js",
  "camelToTitle": "utils.js",
  "capitalize": "utils.js",
  "capitalizeName": "utils.js",
  "capitalizeTitle": "utils.js",
  "caseRE": "utils.js",
  "chalk": "utils.js",
  "chalk2": "utils.js",
  "changeExtension": "utils.js",
  "char2n": "utils.js",
  "check": "utils.js",
  "checkValue": "utils.js",
  "classMixin": "utils.js",
  "coerceArray": "utils.js",
  "coerceToObject": "utils.js",
  "commaRE": "utils.js",
  "comment": "utils.js",
  "compare": "codeOrganizer.js",
  "compareTwoFunctions": "utils.js",
  "compileRE": "utils.js",
  "compose": "utils.js",
  "conditional": "utils.js",
  "conditionalEdit": "utils.js",
  "conditionalPrefix": "Lezer.js",
  "conditionalString": "utils.js",
  "conditionalSuffix": "Lezer.js",
  "copy": "utils.js",
  "countCaptureGroups": "utils.js",
  "countParameters": "utils.js",
  "countParams": "utils.js",
  "CPFBuilder": "utils.js",
  "createAccessors": "utils.js",
  "createFunction": "utils.js",
  "createFuzzyMatch": "utils.js",
  "createVariable": "utils.js",
  "cumulativeAssign": "utils.js",
  "cumulativeSchemaAssign": "utils.js",
  "CumulativeStorage": "utils.js",
  "curry": "utils.js",
  "curry2": "utils.js",
  "curryEnd": "utils.js",
  "curryStart": "utils.js",
  "CustomError": "utils.js",
  "dashCase": "utils.js",
  "dashSplit": "utils.js",
  "datestamp": "utils.js",
  "debounce": "browser-utils.js",
  "debugTest": "utils.js",
  "dedent": "utils.js",
  "dedent2": "utils.js",
  "deepCopy": "utils.js",
  "deepEqual": "utils.js",
  "deepMerge": "utils.js",
  "definedSort": "utils.js",
  "defineGetter": "utils.js",
  "defineProperty": "utils.js",
  "defineVariable": "utils.js",
  "depluralize": "utils.js",
  "dict": "utils.js",
  "dictf": "utils.js",
  "dictGetter": "utils.js",
  "dictSetter": "utils.js",
  "difference": "utils.js",
  "distinct": "utils.js",
  "doublef": "utils.js",
  "doubleQuote": "utils.js",
  "doUntil": "utils.js",
  "doUntil2": "utils.js",
  "dreplace": "utils.js",
  "dsearch": "utils.js",
  "edit": "utils.js",
  "edit2": "utils.js",
  "Element": "utils.js",
  "empty": "utils.js",
  "endsWithWord": "utils.js",
  "entries": "utils.js",
  "equals": "utils.js",
  "escapeHTML": "utils.js",
  "evalErrorHandler": "utils.js",
  "evaluate": "utils.js",
  "evaluate2": "utils.js",
  "exists": "utils.js",
  "exporter": "utils.js",
  "exporter2": "utils.js",
  "extend": "utils.js",
  "extendold": "utils.js",
  "fill": "utils.js",
  "fill2": "utils.js",
  "filter": "utils.js",
  "find": "utils.js",
  "findall": "utils.js",
  "findall2": "utils.js",
  "findIndex": "utils.js",
  "findIndex2": "utils.js",
  "findInMap": "utils.js",
  "findItem2": "utils.js",
  "firstLine": "utils.js",
  "fixPath": "utils.js",
  "fixUrl": "utils.js",
  "flat": "utils.js",
  "flat2D": "utils.js",
  "flatMap": "utils.js",
  "foo": "rp.js",
  "foobar": "utils.js",
  "fooga": "CSSFunctionDict.js",
  "forDoubles": "utils.js",
  "fparse": "utils.js",
  "ftest": "utils.js",
  "functionGetter": "utils.js",
  "fuzzyMatch": "utils.js",
  "fuzzyMatch2": "utils.js",
  "gather": "utils.js",
  "generate": "cabmap.js",
  "getArgs": "utils.js",
  "getBindingName": "utils.js",
  "getBindings2": "utils.js",
  "getCaller": "utils.js",
  "getCaller2": "utils.js",
  "getChunks": "utils.js",
  "getCodeBlockRegex": "utils.js",
  "getCodeChunks": "utils.js",
  "getCodeWords": "utils.js",
  "getCodeWords2": "utils.js",
  "getConfigArg": "utils.js",
  "getConstructorName": "utils.js",
  "getErrorStack": "utils.js",
  "getErrorStack2": "utils.js",
  "getExtension": "utils.js",
  "getFallback": "utils.js",
  "getFileURI": "utils.js",
  "getFirst": "utils.js",
  "getFirstName": "utils.js",
  "getFirstSpaces": "utils.js",
  "getFirstWord": "utils.js",
  "getFrontMatter": "utils.js",
  "getIdentifier": "utils.js",
  "getIdentifiers": "codeOrganizer.js",
  "getIndent": "utils.js",
  "getKwargs": "utils.js",
  "getKwargs2": "utils.js",
  "getLast": "utils.js",
  "getLastSpaces": "utils.js",
  "getLastWord": "utils.js",
  "getLongest": "utils.js",
  "getMethodCaller": "utils.js",
  "getParameters": "utils.js",
  "getParameters2": "utils.js",
  "getQuotes": "utils.js",
  "getSecondSpaces": "utils.js",
  "getset": "utils.js",
  "getShortest": "utils.js",
  "getSpaces": "utils.js",
  "getStackTrace": "utils.js",
  "getTextAndCommand": "utils.js",
  "getWords": "utils.js",
  "green": "utils.js",
  "Group": "utils.js",
  "groupBy": "utils.js",
  "hackReplace": "utils.js",
  "handleError": "utils.js",
  "hasBracket": "utils.js",
  "hasCamelCase": "utils.js",
  "hasCaptureGroup": "utils.js",
  "hasColon": "utils.js",
  "hasComma": "utils.js",
  "hasDollar": "utils.js",
  "hasEquals": "utils.js",
  "hasHtml": "utils.js",
  "hasHtmlSuffix": "utils.js",
  "hasKey": "utils.js",
  "hasLetter": "utils.js",
  "hasNewline": "utils.js",
  "hasNumber": "utils.js",
  "hasSpaces": "utils.js",
  "hasValue": "utils.js",
  "identity": "utils.js",
  "incrementf": "utils.js",
  "indent": "utils.js",
  "indent2": "utils.js",
  "IndexedCache": "utils.js",
  "indexGetter": "utils.js",
  "indexGetter2": "utils.js",
  "inferLang": "utils.js",
  "info": "utils.js",
  "insert": "utils.js",
  "insert2": "utils.js",
  "insert3": "utils.js",
  "intersection": "utils.js",
  "interval": "utils.js",
  "interweave": "utils.js",
  "isArray": "utils.js",
  "isAsyncFunction": "utils.js",
  "isBasicType": "utils.js",
  "isBoolean": "utils.js",
  "isCallable": "utils.js",
  "isCapitalized": "utils.js",
  "isClass": "utils.js",
  "isClassFunction": "utils.js",
  "isClassObject": "utils.js",
  "isColor": "css-utils.js",
  "isCss": "utils.js",
  "isDefined": "utils.js",
  "isError": "utils.js",
  "isEven": "utils.js",
  "isFromMap": "utils.js",
  "isFunction": "utils.js",
  "isHTML": "utils.js",
  "isInitialized": "Puppeteer2.js",
  "isJson": "utils.js",
  "isJsonParsable": "utils.js",
  "isLast": "utils.js",
  "isNestedArray": "utils.js",
  "isNewLine": "utils.js",
  "isNull": "utils.js",
  "isNumber": "utils.js",
  "isObject": "utils.js",
  "isObjectArray": "utils.js",
  "isObjectLiteral": "utils.js",
  "isObjectWithKeys": "utils.js",
  "isOdd": "utils.js",
  "isPercentage": "utils.js",
  "isPlural": "utils.js",
  "isPrimitive": "utils.js",
  "isPrimitiveArray": "utils.js",
  "isPureNumber": "utils.js",
  "isQuote": "utils.js",
  "isRegExp": "utils.js",
  "isRegExpArray": "utils.js",
  "isSet": "utils.js",
  "isSingleLetter": "utils.js",
  "isString": "utils.js",
  "isStringArray": "utils.js",
  "isStringFunction": "utils.js",
  "isSymbol": "utils.js",
  "isThisFunction": "utils.js",
  "isUpperCase": "utils.js",
  "isWhiteSpace": "utils.js",
  "isWord": "utils.js",
  "itemGetter": "utils.js",
  "items": "css-utils.js",
  "iterate": "ma.js",
  "iterator": "utils.js",
  "iteratorWrapper": "utils.js",
  "join": "utils.js",
  "joinSpaces": "utils.js",
  "jspy": "utils.js",
  "keyArrayToObject": "utils.js",
  "KeyError": "utils.js",
  "lastLine": "utils.js",
  "lazyArray": "utils.js",
  "lazyObject": "utils.js",
  "len": "utils.js",
  "linebreakRE": "utils.js",
  "lineCount": "utils.js",
  "lineDitto": "utils.js",
  "lineGetter": "utils.js",
  "lineSplit": "utils.js",
  "list": "utils.js",
  "logConsole": "utils.js",
  "logConsoleRunner": "utils.js",
  "logf": "utils.js",
  "lowerCase": "utils.js",
  "makeFastRunner": "utils.js",
  "makeRunner": "utils.js",
  "makeRunner2": "utils.js",
  "map": "utils.js",
  "mapFilter": "utils.js",
  "mapSort": "utils.js",
  "matchall": "utils.js",
  "matchGetter": "utils.js",
  "merge": "utils.js",
  "merge2": "utils.js",
  "mergeObjectProperties": "utils.js",
  "mergeObjects": "utils.js",
  "mergeOnTop": "utils.js",
  "mergeToObject": "utils.js",
  "methodCase": "utils.js",
  "mget": "utils.js",
  "mixin": "utils.js",
  "mixinAliases": "utils.js",
  "mixinIterator": "utils.js",
  "mixinSetters": "utils.js",
  "modularf": "utils.js",
  "modularIncrement": "utils.js",
  "modularIncrementNumber": "utils.js",
  "mutateFunction": "utils.js",
  "mutation": "utils.js",
  "myError": "utils.js",
  "myJsonParser": "utils.js",
  "n2char": "utils.js",
  "nchalk": "utils.js",
  "nestPush": "utils.js",
  "newlineIndent": "utils.js",
  "no": "utils.js",
  "nodeLog": "ElementController.js",
  "noop": "utils.js",
  "numberBoundarySplit": "utils.js",
  "objectEditor": "utils.js",
  "objectf": "utils.js",
  "objectKeyEditor": "utils.js",
  "objectObjectWalk": "utils.js",
  "objectToString": "utils.js",
  "objectWalk": "utils.js",
  "objectWalk3": "utils.js",
  "once": "utils.js",
  "opposite": "utils.js",
  "orderedSort": "utils.js",
  "overlap": "utils.js",
  "PageStorage": "utils.js",
  "parens": "utils.js",
  "parseError": "utils.js",
  "parseError2": "utils.js",
  "parseJSON": "utils.js",
  "parseTopAttrs": "utils.js",
  "partial": "utils.js",
  "partition": "utils.js",
  "pascalCase": "utils.js",
  "pipe": "utils.js",
  "pluralize": "utils.js",
  "pop": "utils.js",
  "pop2": "utils.js",
  "prepareText": "utils.js",
  "PrevNextMixin": "utils.js",
  "proseCase": "utils.js",
  "push": "utils.js",
  "push2": "utils.js",
  "pushf": "utils.js",
  "QueryList": "utils.js",
  "quotify": "utils.js",
  "raise": "utils.js",
  "range": "utils.js",
  "recursiveObjectEdit": "utils.js",
  "red": "utils.js",
  "reduce": "utils.js",
  "reduce2": "utils.js",
  "reducerStrategy": "utils.js",
  "reduceToString": "utils.js",
  "remove": "utils.js",
  "remove2": "utils.js",
  "removeAllComments": "utils.js",
  "removeComments": "utils.js",
  "removeExtension": "utils.js",
  "removeInlineComments": "utils.js",
  "removeQuotes": "utils.js",
  "rep": "utils.js",
  "repeatUntil": "utils.js",
  "replaceBefore": "utils.js",
  "rescape": "utils.js",
  "reverse": "utils.js",
  "reWrap": "utils.js",
  "reWrap2": "utils.js",
  "rigidSort": "utils.js",
  "round": "utils.js",
  "sandwich": "CSSFunctionDict.js",
  "saybye": "utils.js",
  "sayhi": "utils.js",
  "search": "utils.js",
  "search2": "utils.js",
  "searchAll": "utils.js",
  "searchf": "utils.js",
  "searchf2": "utils.js",
  "secondLine": "utils.js",
  "see": "utils.js",
  "set": "utils.js",
  "shared": "utils.js",
  "singleQuote": "utils.js",
  "sleep": "utils.js",
  "slice": "utils.js",
  "slice2": "utils.js",
  "smallify": "utils.js",
  "smartDedent": "utils.js",
  "smartDedent2": "utils.js",
  "smartDedent3": "utils.js",
  "smartDedent4": "utils.js",
  "smarterIndent": "utils.js",
  "smartestDedent": "utils.js",
  "snakeCase": "utils.js",
  "sort": "utils.js",
  "sortByIndex": "utils.js",
  "sorted": "utils.js",
  "splice": "utils.js",
  "split": "utils.js",
  "splitArray": "utils.js",
  "splitCamel": "utils.js",
  "splitMapJoin": "utils.js",
  "splitOnce": "utils.js",
  "splitThePage": "utils.js",
  "sprawlFactory": "utils.js",
  "stateGetter": "utils.js",
  "stateGetter2": "utils.js",
  "stop": "utils.js",
  "Storage": "utils.js",
  "Store": "utils.js",
  "stringArgument": "utils.js",
  "stringBreaker": "utils.js",
  "stringBreakerBefore": "utils.js",
  "stringCall": "utils.js",
  "stringify": "utils.js",
  "supermix": "utils.js",
  "supermix2": "utils.js",
  "swap": "utils.js",
  "swapKey": "utils.js",
  "swapReplace": "utils.js",
  "tail": "utils.js",
  "templater": "utils.js",
  "test": "utils.js",
  "testf": "utils.js",
  "testf2": "utils.js",
  "textOrJson": "utils.js",
  "timeLog": "utils.js",
  "timestamp": "utils.js",
  "titleCase": "utils.js",
  "toArgument": "utils.js",
  "toArray": "utils.js",
  "toArray2": "utils.js",
  "toJSON": "utils.js",
  "toNestedArray": "utils.js",
  "toNumber": "utils.js",
  "topComment": "utils.js",
  "toPoints": "browser-utils.js",
  "toSpaces": "utils.js",
  "toString": "utils.js",
  "toStringArgument": "utils.js",
  "totalOverlap": "utils.js",
  "toTitleCase": "utils.js",
  "transformObject": "utils.js",
  "Trie": "utils.js",
  "TrieNode": "utils.js",
  "trim": "utils.js",
  "trimAround": "utils.js",
  "type": "utils.js",
  "type2": "utils.js",
  "TypeAssertion": "utils.js",
  "uncapitalize": "utils.js",
  "union": "utils.js",
  "unique": "utils.js",
  "unique2": "utils.js",
  "UniqueStorage": "utils.js",
  "unshift2": "utils.js",
  "unzip": "utils.js",
  "upperCase": "utils.js",
  "vueAssertion": "utils.js",
  "vueCase": "utils.js",
  "vueWrap": "utils.js",
  "walk": "utils.js",
  "warn": "utils.js",
  "Watcher": "utils.js",
  "waterfall": "utils.js",
  "waterfall2": "utils.js",
  "wrap": "utils.js",
  "wrapf": "utils.js",
  "wrapFunctionBefore": "utils.js",
  "xsplit": "utils.js",
  "xsplit2": "utils.js",
  "yes": "utils.js",
  "zip": "utils.js",
  "zip2": "utils.js",
  "aggregateRE": "css-utils.js",
  "attrJump": "Stylesheet.js",
  "buildReference": "Stylesheet.js",
  "colorJump": "Stylesheet.js",
  "colorTransform": "css-utils.js",
  "createCSSObjectParser": "Stylesheet.js",
  "csoParser": "Stylesheet.js",
  "CSSAttributeItems": "css-utils.js",
  "cssColorKeys": "Stylesheet.js",
  "CSSColorObject": "Stylesheet.js",
  "CSSFunctionalObject": "Stylesheet.js",
  "CSSObject": "css-utils.js",
  "CSSPmwh": "Stylesheet.js",
  "defaultDimensionUnits": "Stylesheet.js",
  "incdec": "Stylesheet.js",
  "IncrementalStylesheet": "Stylesheet.js",
  "IndexedCabmap": "Stylesheet.js",
  "IndexedCabmapObject": "Stylesheet.js",
  "numericIncrementRanges": "Stylesheet.js",
  "pixelUnit": "Stylesheet.js",
  "pmwhIncrement": "Stylesheet.js",
  "PresetCabmap": "Stylesheet.js",
  "Stylesheet": "VElementController.js",
  "testing": "css-utils.js",
  "tryWrap": "Stylesheet.js",
  "randomHtmlString": "next.js",
  "sdokf": "next.js",
  "sieveOfEratosthenes": "next.js",
  "border": "CSSFunctionDict.js",
  "borderBottom": "CSSFunctionDict.js",
  "borderLeft": "CSSFunctionDict.js",
  "borderTop": "CSSFunctionDict.js",
  "box": "css-utils.js",
  "colorMatch": "CSSFunctionDict.js",
  "content": "CSSFunctionDict.js",
  "cssBorder": "css-utils.js",
  "cssGrid": "css-utils.js",
  "flex": "CSSFunctionDict.js",
  "getColor": "CSSFunctionDict.js",
  "gradientBoxShadow": "css-utils.js",
  "grid": "CSSFunctionDict.js",
  "parseColor": "CSSFunctionDict.js",
  "positionByPercents": "cssApps.js",
  "positionByPoints": "cssApps.js",
  "randomColor": "css-utils.js",
  "randomColors": "CSSFunctionDict.js",
  "alphabet": "variables.js",
  "BASE_CSS": "variables.js",
  "clipfile": "variables.js",
  "colorBrewer": "variables.js",
  "ColorBrewerAliases": "variables.js",
  "ColorTransformRef": "variables.js",
  "commonExtensions": "variables.js",
  "commonStyleKeys": "variables.js",
  "cssdir": "variables.js",
  "CURRENT_DIRECTORY": "variables.js",
  "DIRECTIONS": "variables.js",
  "dldir": "variables.js",
  "drivedir": "variables.js",
  "emojis": "variables.js",
  "FILE_DICT": "variables.js",
  "FILE_DIRECTORIES": "variables.js",
  "FILE_EXTENSIONS": "variables.js",
  "fileDict": "variables.js",
  "flatColorBrewer": "variables.js",
  "foo1687287516": "variables.js",
  "GoogleFontAliases": "variables.js",
  "HTML_CLOSING_TAGS": "variables.js",
  "HTML_MASTER_KEY_MAP": "variables.js",
  "HTML_NO_CLOSERS": "variables.js",
  "htmlColors": "variables.js",
  "htmlTags": "variables.js",
  "INDEX_HTML_FILE": "variables.js",
  "indexedMaterialColors": "variables.js",
  "javascriptBasicTypes": "variables.js",
  "JavascriptLibraries": "variables.js",
  "JavascriptLibraryItems": "variables.js",
  "javascriptNativeBindings": "variables.js",
  "javascriptNativeFunctions": "variables.js",
  "javascriptOneSpaceWords": "variables.js",
  "javascriptReservedWords": "variables.js",
  "jsdir": "variables.js",
  "jsondir": "variables.js",
  "jsReversed": "variables.js",
  "languageAliases": "variables.js",
  "LOCAL_HOST_URL": "variables.js",
  "logdir": "variables.js",
  "MATERIAL_COLORS_DICT": "variables.js",
  "materialColorAliases": "variables.js",
  "materialColors": "variables.js",
  "mathdir": "variables.js",
  "myColors": "css-utils.js",
  "nativeJavascriptConstructors": "variables.js",
  "nativeWindowKeys": "variables.js",
  "nojiAliases": "variables.js",
  "pdfdir": "variables.js",
  "picdir": "variables.js",
  "PORT": "variables.js",
  "PRIMES": "variables.js",
  "pydir": "variables.js",
  "pythonOneSpaceWords": "variables.js",
  "pythonReservedWords": "variables.js",
  "roygbiv": "variables.js",
  "sandir": "variables.js",
  "shortMaterialColorAliases": "variables.js",
  "speechSynthesisLanguages": "variables.js",
  "startingLineConfigRE": "variables.js",
  "styleCSS": "variables.js",
  "svgTags": "variables.js",
  "tailwindColorKeys": "variables.js",
  "tailwindColors": "variables.js",
  "teachingStyleCSS": "variables.js",
  "TEX_TO_SYMBOL_COUNT": "variables.js",
  "THREE_LETTER_WORDS": "variables.js",
  "TWO_LETTER_WORDS": "variables.js",
  "txtdir": "variables.js",
  "UTF": "variables.js",
  "viableTagRE": "variables.js",
  "vmap": "variables.js",
  "VUE_FOR_DICT": "variables.js",
  "VUE_SINGLE_TO_DOUBLE_REF": "variables.js",
  "vueComponentKeys": "variables.js",
  "vueKeys": "variables.js",
  "baseClusters": "colorClusterSort.js",
  "colorClusterSort": "colorClusterSort.js",
  "oneDimensionSorting": "colorClusterSort.js",
  "sortWithClusters": "colorClusterSort.js",
  "toChroma": "colorClusterSort.js",
  "addExports": "codeOrganizer.js",
  "addExportsAndWrite": "codeOrganizer.js",
  "addFromSourceFile": "codeOrganizer.js",
  "addMissingImports": "codeOrganizer.js",
  "addMissingImportsFromDependencyLibrary": "codeOrganizer.js",
  "addMoreToJavascriptDependenciesFile": "codeOrganizer.js",
  "addToFrom": "codeOrganizer.js",
  "addTopLevelFunctionsAndThenImportTheRest": "codeOrganizer.js",
  "appendToPopped": "codeOrganizer.js",
  "BigLibrary": "codeOrganizer.js",
  "buildMasterFileJson": "codeOrganizer.js",
  "bundleFinalOutput": "codeOrganizer.js",
  "capCase": "codeOrganizer.js",
  "CodeItem": "codeOrganizer.js",
  "CodeLibrary": "codeOrganizer.js",
  "codeOrganizer": "codeOrganizer.js",
  "codeOrganizerTestf": "codeOrganizer.js",
  "CodeState": "codeOrganizer.js",
  "collectExpressions": "codeOrganizer.js",
  "compileJS": "codeOrganizer.js",
  "copyOverMissingFunctions": "codeOrganizer.js",
  "createComponentExports": "codeOrganizer.js",
  "createComponentExportsTest": "codeOrganizer.js",
  "createFile": "codeOrganizer.js",
  "createFile2": "codeOrganizer.js",
  "createFileFromAJS": "codeOrganizer.js",
  "createFileFromFile": "codeOrganizer.js",
  "createGPTBrowserFile": "codeOrganizer.js",
  "createGptOutputFile": "codeOrganizer.js",
  "createNewFileFromTargetFunction": "codeOrganizer.js",
  "createRNG": "codeOrganizer.js",
  "debugWrite": "codeOrganizer.js",
  "defaultCommentAction": "codeOrganizer.js",
  "defaultExportQuery": "codeOrganizer.js",
  "defaultFunctionAction": "codeOrganizer.js",
  "ExportItem": "codeOrganizer.js",
  "extractError": "codeOrganizer.js",
  "fileFromFile": "codeOrganizer.js",
  "filer": "codeOrganizer.js",
  "FileState": "codeOrganizer.js",
  "foo1682543543": "codeOrganizer.js",
  "fulfillImportsFromMaster": "codeOrganizer.js",
  "functionActions": "codeOrganizer.js",
  "getBindingNames": "codeOrganizer.js",
  "getBindings": "codeOrganizer.js",
  "getExports": "codeOrganizer.js",
  "getImportPaths": "codeOrganizer.js",
  "getImports": "codeOrganizer.js",
  "getJavascriptDependencies": "codeOrganizer.js",
  "getMaster": "codeOrganizer.js",
  "getMissing": "codeOrganizer.js",
  "getName": "Lezer.js",
  "getTargets": "codeOrganizer.js",
  "HamChicken": "codeOrganizer.js",
  "handlePopped": "codeOrganizer.js",
  "handleTransfers": "codeOrganizer.js",
  "ImportItem": "codeOrganizer.js",
  "importsAndExports": "codeOrganizer.js",
  "importStatementFromUtils": "codeOrganizer.js",
  "importUtils": "codeOrganizer.js",
  "isCodeState": "codeOrganizer.js",
  "jdjsonfile": "codeOrganizer.js",
  "justTheMainAndItsFunctions": "codeOrganizer.js",
  "makeDependencyMaster": "codeOrganizer.js",
  "makeImportString": "codeOrganizer.js",
  "makeMaster": "codeOrganizer.js",
  "mathState": "codeOrganizer.js",
  "moduleExports": "Lezer.js",
  "moduleImports": "codeOrganizer.js",
  "moveMarkedItems": "codeOrganizer.js",
  "newDependencies": "codeOrganizer.js",
  "nodeFixFilePath": "codeOrganizer.js",
  "organizeDateObjectOptions": "codeOrganizer.js",
  "organizeStuff": "codeOrganizer.js",
  "organizeStuff2": "codeOrganizer.js",
  "organizeStuffOptions": "codeOrganizer.js",
  "popAction": "codeOrganizer.js",
  "recursiveImportDependencyList": "codeOrganizer.js",
  "redoExports": "codeOrganizer.js",
  "returnAnyways": "codeOrganizer.js",
  "reviewItems": "codeOrganizer.js",
  "run": "Lezer.js",
  "runExample": "Lezer.js",
  "seeFileContents": "codeOrganizer.js",
  "setExportAsLastCallable": "codeOrganizer.js",
  "setExports": "codeOrganizer.js",
  "setImports": "codeOrganizer.js",
  "setMissingImports": "codeOrganizer.js",
  "shortModuleImports": "codeOrganizer.js",
  "singleLineJsonArray": "codeOrganizer.js",
  "smallifyTheExportsIntoImports": "codeOrganizer.js",
  "stringsUpFunctionsDown": "codeOrganizer.js",
  "superFileClean": "codeOrganizer.js",
  "targetedEdits": "codeOrganizer.js",
  "testRecursiveDependencies": "codeOrganizer.js",
  "typedActions": "codeOrganizer.js",
  "updateDependencyJSON": "codeOrganizer.js",
  "UTIL_FILES": "codeOrganizer.js",
  "utilState": "codeOrganizer.js",
  "VFo": "codeOrganizer.js",
  "VPageBuilder": "codeOrganizer.js",
  "vvv": "codeOrganizer.js",
  "ask": "Interactive.js",
  "choose": "Interactive.js",
  "chooseIndex": "Interactive.js",
  "createInterface": "Interactive.js",
  "ff": "Interactive.js",
  "fileFinderFactory": "Interactive.js",
  "filePrompt": "Interactive.js",
  "fileStore": "Interactive.js",
  "FileStore": "Interactive.js",
  "interfacePromptAndClose": "Interactive.js",
  "listPrompt": "Interactive.js",
  "Partitioner": "Interactive.js",
  "pick": "Interactive.js",
  "pickAndAddTriggersToIndexedCabmap": "Interactive.js",
  "prompt": "Interactive.js",
  "promptWrite": "Interactive.js",
  "CSSAttributeError": "CSSFunctionDict.js",
  "fontFamily": "CSSFunctionDict.js",
  "fontWeight": "CSSFunctionDict.js",
  "pos": "CSSFunctionDict.js",
  "xy": "CSSFunctionDict.js",
  "a": "Lezer.js",
  "ABC": "Lezer.js",
  "ABFactory": "Lezer.js",
  "argList": "Lezer.js",
  "asdf": "Lezer.js",
  "bin": "Lezer.js",
  "boop": "Lezer.js",
  "buildLezer": "Lezer.js",
  "burry": "Lezer.js",
  "changeEnvAppscriptNames": "Lezer.js",
  "cmBoo": "Lezer.js",
  "cmFoo": "Lezer.js",
  "cmSyntaxSpec": "Lezer.js",
  "collectPropertyNames": "Lezer.js",
  "collectVueData": "Lezer.js",
  "collectVueDataSpec": "Lezer.js",
  "commentOutPython": "Lezer.js",
  "createLezerParser": "Lezer.js",
  "doPython": "Lezer.js",
  "doPythonA": "Lezer.js",
  "doPythonB": "Lezer.js",
  "doTypescript": "Lezer.js",
  "findChild": "Lezer.js",
  "finder": "Lezer.js",
  "findNode": "Lezer.js",
  "firstAndLast": "Lezer.js",
  "fn2017": "Lezer.js",
  "fo": "rp.js",
  "functionDictToGlobalModuleTransformation": "Lezer.js",
  "get": "Lezer.js",
  "getBody": "Lezer.js",
  "getCallableAndArgs": "Lezer.js",
  "getCallableAndArgs2": "Lezer.js",
  "getChild": "Lezer.js",
  "getChildNodeNames": "Lezer.js",
  "getChildNodes": "Lezer.js",
  "getChildren": "Lezer.js",
  "getDescendants": "Lezer.js",
  "getExtendedType": "Lezer.js",
  "getFunctionInfo": "Lezer.js",
  "getHtmlDependencies": "Lezer.js",
  "getImplied2": "Lezer.js",
  "getItems": "Lezer.js",
  "getJavascriptItems": "Lezer.js",
  "getLibrary": "Lezer.js",
  "getNameNode": "Lezer.js",
  "getNode": "Lezer.js",
  "getParams": "Lezer.js",
  "getPrevBinding": "Lezer.js",
  "getQuote": "Lezer.js",
  "getSecondWord": "Lezer.js",
  "getState": "Lezer.js",
  "getType": "Lezer.js",
  "getType2": "Lezer.js",
  "getVariableNameAndValue": "Lezer.js",
  "getVarNode": "Lezer.js",
  "getVarNodes": "Lezer.js",
  "gs": "Lezer.js",
  "has": "Lezer.js",
  "hasName": "Lezer.js",
  "hasQuotes": "Lezer.js",
  "hi": "Lezer.js",
  "ImpliedState": "Lezer.js",
  "isIdentifier": "Lezer.js",
  "iter": "Lezer.js",
  "iterateChildNodes": "Lezer.js",
  "iterCursor": "Lezer.js",
  "javascriptItemSpec": "Lezer.js",
  "javascriptToVimSpec": "Lezer.js",
  "javascriptToVimStringBuilderRef": "Lezer.js",
  "lambdaToBlock": "utils.js",
  "lezer": "Lezer.js",
  "Lezer": "Lezer.js",
  "Lezer2": "Lezer.js",
  "Lezer2Mixins": "Lezer.js",
  "Lezer3": "Lezer.js",
  "lezerf": "Lezer.js",
  "lezerFactory": "Lezer.js",
  "lezerFunctions": "Lezer.js",
  "LezerLanguages": "Lezer.js",
  "LezerMethods": "Lezer.js",
  "LezerPythonMethods": "Lezer.js",
  "LezerRunners": "Lezer.js",
  "lezerSetup": "Lezer.js",
  "lezerSyntaxErrorHandler": "Lezer.js",
  "LifeCycle": "Lezer.js",
  "makeCodemirrorKeymapSpec": "Lezer.js",
  "mapNames": "Lezer.js",
  "moveTo": "Lezer.js",
  "namef": "Lezer.js",
  "namer": "Lezer.js",
  "oldgetImplied": "Lezer.js",
  "oldview": "Lezer.js",
  "parseCMThemes": "Lezer.js",
  "parseType": "Lezer.js",
  "pyConfig": "Lezer.js",
  "pySpec": "Lezer.js",
  "python": "Lezer.js",
  "pythonToJavascript": "Lezer.js",
  "runArunB": "Lezer.js",
  "runCommandFromLine": "Lezer.js",
  "runFunction": "Lezer.js",
  "runLezer": "Lezer.js",
  "runner": "Lezer.js",
  "runnner": "Lezer.js",
  "Sdf": "Lezer.js",
  "setup": "Lezer.js",
  "simpleLezer": "Lezer.js",
  "something": "Lezer.js",
  "spaceOnBothSides": "Lezer.js",
  "sprawlRange": "Lezer.js",
  "stringBuilder": "Lezer.js",
  "stringBuilder2": "Lezer.js",
  "StringState": "Lezer.js",
  "svgNames": "Lezer.js",
  "svgNameSpec": "Lezer.js",
  "topLevel": "Lezer.js",
  "TopLevelRunners": "Lezer.js",
  "topNode": "Lezer.js",
  "traverse": "Lezer.js",
  "typeMapStrategy": "Lezer.js",
  "typescriptTestSpec": "Lezer.js",
  "typescriptToJavascript": "Lezer.js",
  "vd": "Lezer.js",
  "VFosdfs": "Lezer.js",
  "view": "Lezer.js",
  "vn": "Lezer.js",
  "Vob": "Lezer.js",
  "xxgetFunctionInfo": "Lezer.js",
  "_boxShadows": "css-utils.js",
  "arrayCabmap": "cabmap.js",
  "boxShadows": "css-utils.js",
  "build": "utils.js",
  "cabmap": "cabmap.js",
  "indexedCabmap": "cabmap.js",
  "indexedCabmapItems": "cabmap.js",
  "str1686367165": "cabmap.js",
  "addStuffToStore": "css-utils.js",
  "asd": "css-utils.js",
  "assignStyle": "browser-utils.js",
  "bleCSS": "css-utils.js",
  "bleCSSPostParse": "css-utils.js",
  "boxer": "css-utils.js",
  "cab": "css-utils.js",
  "createStyleFunction": "css-utils.js",
  "createStyleObjects": "css-utils.js",
  "createStyleParser": "css-utils.js",
  "CSS_FONT_REF": "css-utils.js",
  "css2Fonts": "css-utils.js",
  "cssAddImplicitProperties": "css-utils.js",
  "cssAddPeriod": "css-utils.js",
  "cssAddUnit": "css-utils.js",
  "CSSAliases": "css-utils.js",
  "cssAliasIncrement": "css-utils.js",
  "cssAliasIncrementRef": "css-utils.js",
  "cssBorderHelper": "css-utils.js",
  "CSSBuilder": "css-utils.js",
  "cssCak": "css-utils.js",
  "cssColon": "css-utils.js",
  "cssDontAddPeriodRE": "css-utils.js",
  "cssEntry": "css-utils.js",
  "CSSFill": "css-utils.js",
  "cssFixImplicit": "css-utils.js",
  "cssFont": "css-utils.js",
  "cssFontImport": "css-utils.js",
  "cssFromObject": "css-utils.js",
  "CSSFunctionDict": "css-utils.js",
  "CSSFunctionDict2": "css-utils.js",
  "CSSFunctions": "css-utils.js",
  "cssGridArea": "css-utils.js",
  "cssGridFromNumber": "css-utils.js",
  "cssGridHelper": "css-utils.js",
  "cssIncrement": "css-utils.js",
  "cssIncrement2": "css-utils.js",
  "cssIncrement3": "css-utils.js",
  "cssIsPseudoSelector": "css-utils.js",
  "cssMerge": "css-utils.js",
  "cssNamedFunctionDict": "css-utils.js",
  "cssObject": "css-utils.js",
  "cssPage": "css-utils.js",
  "cssPage2": "css-utils.js",
  "cssParseColon": "css-utils.js",
  "cssParser": "css-utils.js",
  "cssParser2": "css-utils.js",
  "cssPosition": "css-utils.js",
  "cssReduceKeyToFunction": "css-utils.js",
  "cssSetupString": "css-utils.js",
  "cssSpec": "css-utils.js",
  "cssString": "css-utils.js",
  "cssString2": "css-utils.js",
  "cssStringArrayString": "css-utils.js",
  "cssStringToArray": "css-utils.js",
  "cssStringToDict": "css-utils.js",
  "CSSValueAliases": "css-utils.js",
  "DictionaryTokenizer": "css-utils.js",
  "editStyleMaster": "css-utils.js",
  "excludeFromChildrenListRE": "css-utils.js",
  "fixChildParentPosition": "css-utils.js",
  "fixObjectStyle": "css-utils.js",
  "getPos": "css-utils.js",
  "getStyleFromLine": "css-utils.js",
  "getStylePayload": "css-utils.js",
  "hasUnit": "css-utils.js",
  "i3ref": "css-utils.js",
  "incrementMaster": "css-utils.js",
  "isCSS": "css-utils.js",
  "isElementTag": "css-utils.js",
  "main": "serve_html_file.js",
  "makeCSSObject": "css-utils.js",
  "mapObject": "css-utils.js",
  "marginBottom": "css-utils.js",
  "mixinStyleSetters": "css-utils.js",
  "objectStyleParser": "css-utils.js",
  "ocssIncrement3": "css-utils.js",
  "PresetAliases": "css-utils.js",
  "stringStyleParser": "css-utils.js",
  "STYLE_OBJECT_MASTER": "css-utils.js",
  "styleParser": "css-utils.js",
  "Stylesheet2": "VElementController.js",
  "styleString": "css-utils.js",
  "svgColor": "css-utils.js",
  "tester": "css-utils.js",
  "addElementProperties": "browser-utils.js",
  "addEventListener": "browser-utils.js",
  "browserClick": "browser-utils.js",
  "calculateReadingTime": "browser-utils.js",
  "copyCode": "browser-utils.js",
  "createClickEvent": "browser-utils.js",
  "createElement": "browser-utils.js",
  "createXPath": "browser-utils.js",
  "cssLoader": "browser-utils.js",
  "download": "browser-utils.js",
  "downloadBlob": "browser-utils.js",
  "downloadFromBackEnd": "browser-utils.js",
  "downloadGooglePDF": "browser-utils.js",
  "downloadGooglePDF2": "browser-utils.js",
  "downloadPdfFromUrl": "browser-utils.js",
  "elementGetter": "browser-utils.js",
  "elementInfo": "browser-utils.js",
  "elementStyleInfo": "browser-utils.js",
  "elt": "browser-utils.js",
  "elt2": "browser-utils.js",
  "elt3": "browser-utils.js",
  "fixSelector": "browser-utils.js",
  "focus": "browser-utils.js",
  "fontLoader": "browser-utils.js",
  "getBoundingClientRect": "browser-utils.js",
  "getChildHeights": "browser-utils.js",
  "getChildRects": "browser-utils.js",
  "getClipboard": "browser-utils.js",
  "getComputedCSSValues": "browser-utils.js",
  "getElementChildren": "browser-utils.js",
  "getElementHeightInPoints": "browser-utils.js",
  "getElementRectInPoints": "browser-utils.js",
  "getKeyArg": "browser-utils.js",
  "getKeys": "utils.js",
  "getLocalHost": "browser-utils.js",
  "getPointHeight": "browser-utils.js",
  "getSelectionText": "browser-utils.js",
  "getWindowKeys": "browser-utils.js",
  "google": "browser-utils.js",
  "googleFileDownload": "browser-utils.js",
  "highlight": "browser-utils.js",
  "highlightCode": "browser-utils.js",
  "html": "browser-utils.js",
  "html1": "browser-utils.js",
  "html2": "browser-utils.js",
  "insertElement": "browser-utils.js",
  "isBrowser": "browser-utils.js",
  "isElement": "browser-utils.js",
  "isEmptyArray": "utils.js",
  "isMac": "browser-utils.js",
  "isMobile": "browser-utils.js",
  "isPuppeteer": "browser-utils.js",
  "isVNode": "browser-utils.js",
  "isVue": "vueSetup.js",
  "javascript": "browser-utils.js",
  "javascript1": "browser-utils.js",
  "javascript1A": "browser-utils.js",
  "javascript2": "browser-utils.js",
  "javascript3": "browser-utils.js",
  "keyboardAliases": "browser-utils.js",
  "keypressDict": "browser-utils.js",
  "lineDetectionWrapper": "browser-utils.js",
  "localPost": "browser-utils.js",
  "localRequest": "browser-utils.js",
  "makeElement": "browser-utils.js",
  "mouse": "browser-utils.js",
  "mouseListener": "browser-utils.js",
  "postLocalHost": "browser-utils.js",
  "preventDefault": "browser-utils.js",
  "puppetString": "browser-utils.js",
  "qsa": "browser-utils.js",
  "querySelectorAll": "browser-utils.js",
  "removeElement": "browser-utils.js",
  "removeEventListener": "browser-utils.js",
  "scroll": "browser-utils.js",
  "scrollDown": "browser-utils.js",
  "scrollToElement": "browser-utils.js",
  "setAttributes": "browser-utils.js",
  "setClipboard": "browser-utils.js",
  "StyleDict": "browser-utils.js",
  "superElementInfo": "browser-utils.js",
  "xPathQuerySelectorAll": "browser-utils.js",
  "buildTree": "ec-main.js",
  "CLEAR": "VueWindowListener.js",
  "ContextHandle": "VueWindowListener.js",
  "contextHandleMixSpec": "VueWindowListener.js",
  "createDocument": "VElementController.js",
  "EARLYRETURN": "ElementController.js",
  "ECElement": "VElementController.js",
  "ECState": "VElementController.js",
  "editObject2": "VElementController.js",
  "ElementControllerPlugin": "VElementController.js",
  "ModalPlugin": "VElementController.js",
  "removeStylesheet": "VElementController.js",
  "TestingLifeCycleHooksPlugin": "ElementController.js",
  "typist": "VElementController.js",
  "UploadPluginFunction": "VElementController.js",
  "VElementController": "ec-main.js",
  "VerySimpleHandle": "ElementController.js",
  "VFoo": "ElementController.js",
  "VGoo": "ElementController.js",
  "VMain": "ElementController.js",
  "WindowStoragePlugin": "VElementController.js",
  "ECHandle": "ec-handle.js",
  "handle": "ec-handle.js",
  "preHandle": "ec-handle.js",
  "VueWindowListener": "VueWindowListener.js",
  "collectComponentBindings": "setupComponent.js",
  "collectThisKeys": "setupComponent.js",
  "setupComponent": "setupComponent.js",
  "setupData": "setupComponent.js",
  "setupMethods": "setupComponent.js",
  "setupMixed": "setupComponent.js",
  "setupNextPrev": "setupComponent.js",
  "setupString": "setupComponent.js",
  "setupTemplate": "setupComponent.js",
  "setupWatchers": "setupComponent.js",
  "appWrapper": "vueSetup.js",
  "createVue": "vueSetup.js",
  "isRoot": "vueSetup.js",
  "isRootDescendant": "vueSetup.js",
  "isVob": "vueSetup.js",
  "isVueComponent": "vueSetup.js",
  "isVueDirective": "vueSetup.js",
  "MixinDataPlugin": "vueSetup.js",
  "nameIt": "vueSetup.js",
  "propIt": "vueSetup.js",
  "registerFunctionsFactory": "vueSetup.js",
  "registerPrototypeFunction": "vueSetup.js",
  "renderWrapper": "vueSetup.js",
  "simpleWrapper": "vueSetup.js",
  "transitionWrapper": "vueSetup.js",
  "vueGetCountFactory": "vueSetup.js",
  "vueInfo": "vueSetup.js",
  "vueLogger": "vueSetup.js",
  "vueName": "vueSetup.js",
  "vueRenderer": "vueSetup.js",
  "vueSetup": "vueSetup.js",
  "main2": "serve_html_file.js",
  "addEquals": "ma.js",
  "addMathComma": "ma.js",
  "addRandomDecimals": "ma.js",
  "allEqual": "ma.js",
  "arrayGrid": "ma.js",
  "calc": "ma.js",
  "cartesianProduct": "ma.js",
  "closerTo": "ma.js",
  "coercePositiveNumber": "ma.js",
  "coinflip": "ma.js",
  "controlDelimiters": "ma.js",
  "cosine": "ma.js",
  "cossin": "ma.js",
  "countPalindromicFactors": "ma.js",
  "decimalShift": "ma.js",
  "digitSum": "ma.js",
  "divide": "ma.js",
  "divmod": "ma.js",
  "fixFloatingPoint": "ma.js",
  "fixFloatingPointRE": "ma.js",
  "forij": "ma.js",
  "gcd": "ma.js",
  "getCombinations": "ma.js",
  "getDecimalLength": "ma.js",
  "getDigitAtPosition": "ma.js",
  "getFactors": "ma.js",
  "getMathTokens": "ma.js",
  "getNumber": "ma.js",
  "getNumberAndZeroes": "ma.js",
  "getNumberData": "ma.js",
  "getNumbers": "ma.js",
  "getOperator": "ma.js",
  "getPrimes": "ma.js",
  "getVariables": "ma.js",
  "greaterThan": "ma.js",
  "hasDecimal": "ma.js",
  "hasLatex": "ma.js",
  "infuseNumbers": "ma.js",
  "isCoprime": "ma.js",
  "isDecimal": "ma.js",
  "isDivisible": "ma.js",
  "isEquation": "ma.js",
  "isExpression": "ma.js",
  "isFraction": "ma.js",
  "isInteger": "ma.js",
  "isLongDecimal": "ma.js",
  "isNegative": "ma.js",
  "isPalindrome": "ma.js",
  "isPositive": "ma.js",
  "isPrime": "ma.js",
  "isSquare": "ma.js",
  "iterGroup": "ma.js",
  "jsrange": "ma.js",
  "katexLongDivision": "ma.js",
  "lcm": "ma.js",
  "lessThan": "ma.js",
  "longShort": "ma.js",
  "lowHigh": "ma.js",
  "mathTemplater": "ma.js",
  "multiplesOf": "ma.js",
  "multiply": "ma.js",
  "normalizePositive": "ma.js",
  "numbered": "ma.js",
  "numberf": "ma.js",
  "numbergen": "ma.js",
  "Numbergen": "ma.js",
  "opDelimiters": "ma.js",
  "percentOf": "ma.js",
  "power": "ma.js",
  "power10": "ma.js",
  "randomIndexes": "ma.js",
  "randomPick": "ma.js",
  "rangeFromString": "ma.js",
  "rng": "ma.js",
  "rngAround": "ma.js",
  "rngDecimal": "ma.js",
  "roundToNearest": "ma.js",
  "roundToZero": "ma.js",
  "shuffle": "ma.js",
  "simplify": "ma.js",
  "sine": "ma.js",
  "smallBig": "ma.js",
  "square": "ma.js",
  "sum": "ma.js",
  "tally": "ma.js",
  "Tally": "ma.js",
  "toDegrees": "ma.js",
  "toPercentage": "ma.js",
  "toRadians": "ma.js",
  "truncate": "ma.js",
  "getPrintPath": "Puppeteer2.js",
  "increment": "Puppeteer2.js",
  "print": "Puppeteer2.js",
  "printPDF": "Puppeteer2.js",
  "PUPPETEER_ERROR_STATUS": "Puppeteer2.js",
  "Puppeteer2": "Puppeteer2.js",
  "PuppeteerDefaultOptions": "Puppeteer2.js",
  "PuppeteerMixins": "Puppeteer2.js",
  "puppetParser": "Puppeteer2.js",
  "runPuppeteer": "Puppeteer2.js",
  "screenshot": "Puppeteer2.js",
  "windowSet": "Puppeteer2.js",
  "addConst": "utils.js",
  "Axis": "utils.js",
  "buildFunction": "utils.js",
  "clamp": "utils.js",
  "clamper": "utils.js",
  "copyBuffer": "utils.js",
  "data": "utils.js",
  "durationWeeks": "utils.js",
  "foo1686063379": "utils.js",
  "fromContinuedFraction": "utils.js",
  "getHourlyRate": "utils.js",
  "groceryList": "utils.js",
  "historyKeymap": "utils.js",
  "hoursPerDay": "utils.js",
  "implicitTransform": "utils.js",
  "interpolateRange": "utils.js",
  "inverseLerp": "utils.js",
  "invlerp": "utils.js",
  "jwrite": "utils.js",
  "keyLoggerFn": "utils.js",
  "lerp": "utils.js",
  "lohi": "utils.js",
  "normalize": "utils.js",
  "normalizer": "utils.js",
  "numberArray": "utils.js",
  "readParse": "utils.js",
  "ReadParse": "utils.js",
  "reducer": "utils.js",
  "rp": "utils.js",
  "Scale": "utils.js",
  "squareRootInterpolation": "utils.js",
  "temp": "utils.js",
  "textAlign": "utils.js",
  "toContinuedFraction": "utils.js",
  "totalEarnings": "utils.js",
  "transform": "utils.js",
  "Transform": "utils.js",
  "Transformer": "utils.js",
  "undo": "utils.js",
  "x": "utils.js",
  "y": "utils.js",
  "cssGenerateBorderKeys": "rp.js",
  "getCssKeys": "rp.js",
  "parseHistoryJson": "rp.js",
  "postParseHistoryJson": "rp.js",
  "__touched__": [
    "node-utils.js",
    "utils.js",
    "Stylesheet.js",
    "next.js",
    "cssApps.js",
    "variables.js",
    "colorClusterSort.js",
    "codeOrganizer.js",
    "Interactive.js",
    "CSSFunctionDict.js",
    "Lezer.js",
    "cabmap.js",
    "css-utils.js",
    "browser-utils.js",
    "ElementController.js",
    "VElementController.js",
    "ec-main.js",
    "ec-handle.js",
    "VueWindowListener.js",
    "setupComponent.js",
    "vueSetup.js",
    "serve_html_file.js",
    "ma.js",
    "Puppeteer2.js",
    "utils.js",
    "rp.js"
  ],
  "vueError": "vueSetup.js",
  "nestedWrapper": "vueSetup.js",
  "cssGetName": "css-utils.js",
  "cssGetKey": "css-utils.js",
  "kdog3682": "",
  "element": ""
}
